---
title: ğŸšŒ JNI
summary: javaæœ¬åœ°ä»£ç æ”¯æŒ
date: 2025-08-05
authors:
  - admin
tags:
  - javaä¸è¯­è¨€äº¤äº’
---
## JNI

### ä»€ä¹ˆæ˜¯ JNI

JNIï¼ˆJava Native Interfaceï¼ŒJavaæœ¬åœ°æ¥å£ï¼‰æ˜¯Javaå¹³å°æä¾›çš„ä¸€ç§ç¼–ç¨‹æ¥å£ï¼Œå…è®¸Javaä»£ç ä¸å…¶ä»–è¯­è¨€ï¼ˆä¸»è¦æ˜¯C/C++ï¼‰ç¼–å†™çš„æœ¬åœ°ä»£ç è¿›è¡Œäº¤äº’ã€‚é€šè¿‡JNIï¼ŒJavaç¨‹åºå¯ä»¥è°ƒç”¨æœ¬åœ°æ–¹æ³•ï¼Œä¹Ÿå¯ä»¥è¢«æœ¬åœ°ä»£ç è°ƒç”¨ï¼Œå®ç°ä¸æ“ä½œç³»ç»Ÿåº•å±‚æˆ–ç¬¬ä¸‰æ–¹åº“çš„é›†æˆã€‚

---

### JNI çš„ä¼˜ç¼ºç‚¹

**ä¼˜ç‚¹ï¼š**
- å¯ä»¥è°ƒç”¨C/C++ç­‰æœ¬åœ°ä»£ç ï¼Œæå‡æ€§èƒ½ï¼Œé€‚åˆå¯¹æ€§èƒ½è¦æ±‚é«˜çš„åœºæ™¯ã€‚
- èƒ½è®¿é—®æ“ä½œç³»ç»Ÿåº•å±‚èµ„æºæˆ–ç¡¬ä»¶ï¼Œæ‰©å±•Javaçš„èƒ½åŠ›ã€‚
- ä¾¿äºå¤ç”¨å·²æœ‰çš„æœ¬åœ°åº“æˆ–ç¬¬ä¸‰æ–¹åº“ã€‚

**ç¼ºç‚¹ï¼š**
- ç¼–ç¨‹å¤æ‚ï¼Œå¼€å‘å’Œè°ƒè¯•éš¾åº¦è¾ƒå¤§ã€‚
- è·¨å¹³å°æ€§å˜å·®ï¼Œä¾èµ–æœ¬åœ°å¹³å°å’Œç¼–è¯‘ç¯å¢ƒã€‚
- å¯èƒ½å¼•å…¥å†…å­˜æ³„æ¼ã€å´©æºƒç­‰å®‰å…¨éšæ‚£ã€‚
- å½±å“Javaåº”ç”¨çš„å¯ç§»æ¤æ€§å’Œç¨³å®šæ€§ã€‚

---

### Java ä¸­å¦‚ä½•ä½¿ç”¨ JNI

#### 1. åˆ›å»º Java ä»£ç 

**Example.java**
```java
public class Example {
    // å£°æ˜æœ¬åœ°æ–¹æ³•
    public native void helloFromSo();

    // åŠ è½½å…±äº«åº“
    static {
        System.loadLibrary("example"); // ä¸éœ€è¦åŠ å‰ç¼€ "lib" å’Œåç¼€ ".so"
    }

    public static void main(String[] args) {
        Example example = new Example();
        example.helloFromSo(); // è°ƒç”¨æœ¬åœ°æ–¹æ³•
    }
}
```

#### 2. ç¼–è¯‘ Java ä»£ç 

```bash
/usr/local/java/jdk1.8.0_121/bin/javac Example.java
```

#### 3. ç”± Java ä»£ç ç”Ÿæˆå¤´æ–‡ä»¶

```bash
/usr/local/java/jdk1.8.0_121/bin/javah -jni Example
```

---

### 4. ä½¿ç”¨ C å®ç°æ–¹æ³•

**example.c**
```c
#include <jni.h>
#include <stdio.h>
#include "Example.h"

JNIEXPORT void JNICALL Java_Example_helloFromSo(JNIEnv *env, jobject obj) {
    printf("Hello from JNI!\n");
}
```

#### 5. ç¼–è¯‘ç”Ÿæˆæ ‡å‡†é“¾æ¥åº“

ä¾èµ– jni.h å’Œ jni_md.h å¤´æ–‡ä»¶ï¼Œéœ€è¦æŒ‡å®šè·¯å¾„ï¼š

```bash
gcc -I /usr/local/java/jdk1.8.0_121/include -I /usr/local/java/jdk1.8.0_121/include/linux -shared -o libexample.so -fPIC example.c
```

#### 6. è®¾ç½®ç¯å¢ƒå˜é‡ï¼Œå¼•ç”¨æ ‡å‡†è¿æ¥åº“

å°† .so æ–‡ä»¶æ”¾å…¥ /usr/lib64 ä¸­ï¼Œæˆ–è€…è®¾ç½®ç¯å¢ƒå˜é‡ï¼š

```bash
export LD_LIBRARY_PATH=.:$LD_LIBRARY_PATH
```

#### 7. è¿è¡Œç¨‹åº

```bash
/usr/local/java/jdk1.8.0_121/bin/java Example
```

---

### JVM æ˜¯å¦‚ä½•æ‰§è¡Œ native æ–¹æ³•

å½“ Java ç¨‹åºè°ƒç”¨ native æ–¹æ³•æ—¶ï¼ŒJVM çš„æ‰§è¡Œè¿‡ç¨‹å¦‚ä¸‹ï¼š

#### 1. Java ç¼–è¯‘ç”Ÿæˆ class ç»“æ„
```java
public class Demo {
    public static void main(String[] args) {
        int sum = sum(1, 2);
        System.out.println(sum);
    }

    public static native int sum(int a, int b);
}
```
```bash
javap -c -s -v Demo.class
```

```
Classfile /C:/Users/chaoying/IdeaProjects/LinuxSo/LinuxSo/src/main/java/Demo.class
  Last modified 2025-5-16; size 420 bytes
  MD5 checksum f6487b784931d6c10816100764ac1295
  Compiled from "Demo.java"
public class Demo
  minor version: 0
  major version: 52
  flags: ACC_PUBLIC, ACC_SUPER
Constant pool:
   #1 = Methodref          #6.#17         // java/lang/Object."<init>":()V
   #2 = Methodref          #5.#18         // Demo.sum:(II)I
   #3 = Fieldref           #19.#20        // java/lang/System.out:Ljava/io/PrintStream;
   #4 = Methodref          #21.#22        // java/io/PrintStream.println:(I)V
   #5 = Class              #23            // Demo
   #6 = Class              #24            // java/lang/Object
   #7 = Utf8               <init>
   #8 = Utf8               ()V
   #9 = Utf8               Code
  #10 = Utf8               LineNumberTable
  #11 = Utf8               main
  #12 = Utf8               ([Ljava/lang/String;)V
  #13 = Utf8               sum
  #14 = Utf8               (II)I
  #15 = Utf8               SourceFile
  #16 = Utf8               Demo.java
  #17 = NameAndType        #7:#8          // "<init>":()V
  #18 = NameAndType        #13:#14        // sum:(II)I
  #19 = Class              #25            // java/lang/System
  #20 = NameAndType        #26:#27        // out:Ljava/io/PrintStream;
  #21 = Class              #28            // java/io/PrintStream
  #22 = NameAndType        #29:#30        // println:(I)V
  #23 = Utf8               Demo
  #24 = Utf8               java/lang/Object
  #25 = Utf8               java/lang/System
  #26 = Utf8               out
  #27 = Utf8               Ljava/io/PrintStream;
  #28 = Utf8               java/io/PrintStream
  #29 = Utf8               println
  #30 = Utf8               (I)V
{
  public Demo();
    descriptor: ()V
    flags: ACC_PUBLIC
    Code:
      stack=1, locals=1, args_size=1
         0: aload_0
         1: invokespecial #1                  // Method java/lang/Object."<init>":()V
         4: return
      LineNumberTable:
        line 1: 0

  public static void main(java.lang.String[]);
    descriptor: ([Ljava/lang/String;)V
    flags: ACC_PUBLIC, ACC_STATIC
    Code:
      stack=2, locals=2, args_size=1
         0: iconst_1
         1: iconst_2
         2: invokestatic  #2                  // Method sum:(II)I
         5: istore_1
         6: getstatic     #3                  // Field java/lang/System.out:Ljava/io/PrintStream;
         9: iload_1
        10: invokevirtual #4                  // Method java/io/PrintStream.println:(I)V
        13: return
      LineNumberTable:
        line 3: 0
        line 4: 6
        line 5: 13

  public static native int sum(int, int);
    descriptor: (II)I
    flags: ACC_PUBLIC, ACC_STATIC, ACC_NATIVE
}
SourceFile: "Demo.java"
```
å…¶ä¸­nativeæ–¹æ³•ä¼šç”ŸæˆACC_NATIVEæ ‡è¯†

#### 2. Java ç±»åŠ è½½

ç±»åŠ è½½å™¨ï¼ˆClassLoaderï¼‰å°† .class æ–‡ä»¶åŠ è½½åˆ° JVM å†…å­˜ä¸­ï¼Œnative æ–¹æ³•çš„ä¿¡æ¯ä¹Ÿè¢«åŠ è½½åˆ°æ–¹æ³•åŒºã€‚

#### 3. ç¨‹åºæ‰§è¡Œæµç¨‹

- å¯¹äº JVM æ¥è¯´ï¼Œä¸€ä¸ª Java ç¨‹åºå¯¹åº”ä¸€ä¸ªè™šæ‹Ÿæœºæ ˆï¼ˆJava Stackï¼‰ã€‚
- å½“ Java æ–¹æ³•è°ƒç”¨ native æ–¹æ³•æ—¶ï¼ŒJVM ä¼šä¸ºå½“å‰çº¿ç¨‹åˆ›å»ºä¸€ä¸ªæœ¬åœ°æ–¹æ³•æ ˆï¼ˆNative Stackï¼‰ï¼Œå¹¶å°†ç¨‹åºè®¡æ•°å™¨ï¼ˆPCï¼‰è·³è½¬åˆ° native æ–¹æ³•çš„å†…å­˜åœ°å€ã€‚
- JVM æŸ¥æ‰¾å¹¶è°ƒç”¨æœ¬åœ°æ–¹æ³•å®ç°ï¼ˆå¦‚åŠ¨æ€é“¾æ¥åº“ä¸­çš„å‡½æ•°ï¼‰ï¼Œå¹¶æŒ‰ç…§é¡ºåºæ‰§è¡Œæœ¬åœ°ä»£ç é€»è¾‘ã€‚
- æœ¬åœ°æ–¹æ³•æ‰§è¡Œå®Œæ¯•åï¼Œå¼¹å‡ºæœ¬åœ°æ–¹æ³•æ ˆï¼Œç¨‹åºè®¡æ•°å™¨è·³å› Java è™šæ‹Ÿæœºæ ˆï¼Œç»§ç»­æ‰§è¡Œåç»­ Java ä»£ç ã€‚

#### 4. æœ¬åœ°æ–¹æ³•æ ¼å¼è¦æ±‚

- ä¸ºäº†è®© JVM èƒ½æ­£ç¡®è§£æå’ŒåŠ è½½æœ¬åœ°æ–¹æ³•ï¼Œæœ¬åœ°æ–¹æ³•éœ€è¦éµå¾ªç‰¹å®šçš„æ ¼å¼ã€‚
- å¯ä»¥é€šè¿‡ `javah` å·¥å…·æ ¹æ® Java ç±»è‡ªåŠ¨ç”Ÿæˆå¯¹åº”çš„ C/C++ å¤´æ–‡ä»¶ï¼Œç¡®ä¿æ–¹æ³•ç­¾åå’Œå‚æ•°ç±»å‹æ­£ç¡®åŒ¹é…ã€‚
- å…·ä½“çš„æœ¬åœ°æ–¹æ³•å®ç°ç”±ä¸šåŠ¡ä»£ç æ§åˆ¶ã€‚

---